node_graph/Diagram.py
node_graph/__init__.py
node_graph/example.py
node_graph/__pycache__/Diagram.cpython-312.pyc
node_graph/__pycache__/__init__.cpython-312.pyc
node_graph/frontend/.eslintrc.cjs
node_graph/frontend/.gitignore
node_graph/frontend/README.md
node_graph/frontend/index.html
node_graph/frontend/package-lock.json
node_graph/frontend/package.json
node_graph/frontend/postcss.config.js
node_graph/frontend/tailwind.config.js
node_graph/frontend/vite.config.js
node_graph/frontend/dist/index.html
node_graph/frontend/dist/vite.svg
node_graph/frontend/dist/assets/index-CdFos-TN.js
node_graph/frontend/dist/assets/index-DuAtux4K.css
node_graph/frontend/dist/assets/index-DxQ4CDjE.js
node_graph/frontend/public/vite.svg
node_graph/frontend/src/GetIcon.jsx
node_graph/frontend/src/MyComponent.jsx
node_graph/frontend/src/Node.jsx
node_graph/frontend/src/Sidebar.jsx
node_graph/frontend/src/base.css
node_graph/frontend/src/index.css
node_graph/frontend/src/main.jsx
node_graph/frontend/src/sidebar.css
node_graph/frontend/src/assets/react.svg
streamlit_flow_node_graph-0.0.10.dist-info/LICENSE
streamlit_flow_node_graph-0.0.10.dist-info/METADATA
streamlit_flow_node_graph-0.0.10.dist-info/WHEEL
streamlit_flow_node_graph-0.0.10.dist-info/top_level.txt
streamlit_flow_node_graph-0.0.10.dist-info/RECORD
